{
  "cli": {
    "version": ">= 5.0.0",
    "appVersionSource": "remote"
  },
  "build": {
    "development": {
      "developmentClient": true,
      "distribution": "internal",
      "ios": {
        "simulator": true
      }
    },
    "preview": {
      "android": {
        "buildType": "apk",
        "gradleCommand": ":app:assembleRelease"
      },
      "ios": {
        "simulator": false,
        "buildConfiguration": "Release"
      },
      "distribution": "internal",
      "env": {
        "NODE_ENV": "production",
        "EXPO_NO_TYPESCRIPT_CHECK": "1",
        "CI": "false",
        "EXPO_NO_METRO_LAZY": "1"
      },
      "node": "20.19.4"
    },
    "production": {
      "android": {
        "buildType": "apk",
        "gradleCommand": ":app:assembleRelease"
      },
      "ios": {
        "simulator": false,
        "buildConfiguration": "Release"
      },
      "autoIncrement": true,
      "env": {
        "NODE_ENV": "production",
        "EXPO_NO_TYPESCRIPT_CHECK": "1",
        "CI": "false",
        "EXPO_NO_METRO_LAZY": "1"
      },
      "node": "20.19.4"
    }
  },
  "submit": {
    "production": {
      "ios": {
        "appleId": "your-apple-id@example.com",
        "ascAppId": "your-app-store-connect-app-id",
        "appleTeamId": "your-apple-team-id"
      }
    }
  }
}
